helloq365-1.0.0.dist-info/METADATA
helloq365-1.0.0.dist-info/WHEEL
helloq365/__init__.py
helloq365/helloq365.cpython-310-x86_64-linux-gnu.so
helloq365-1.0.0.dist-info/RECORD
