Metadata-Version: 2.1
Name: helloq365
Version: 1.0.0
